aichatlite_web/__init__.py
aichatlite_web/core/__init__.py
aichatlite_web/core/base.py
aichatlite_web/core/baseprompt.py
aichatlite_web/core/const.py
aichatlite_web/core/features/__init__.py
aichatlite_web/core/features/feature_main.py
aichatlite_web/core/features/handle_google_searchai.py
aichatlite_web/core/features/handle_pdf.py
aichatlite_web/core/features/handle_search_ai.py
aichatlite_web/core/omni_mixin.py
aichatlite_web/core/prompts.py
aichatlite_web/core/streamlit_app.py
aichatlite_web/core/streamlit_css.py
aichatlite_web/server_main.py
aichatlite_web/utils/__init__.py
aichatlite_web/utils/prompt_names_fetcher.py
chat_gui.py
chat_run.py
aichatlite_web-0.0.10.dist-info/METADATA
aichatlite_web-0.0.10.dist-info/WHEEL
aichatlite_web-0.0.10.dist-info/entry_points.txt
aichatlite_web-0.0.10.dist-info/RECORD
