Metadata-Version: 2.1
Name: aichatlite-web
Version: 0.0.10
Summary: claude chat
Home-page: https://github.cov0m/username/sa
License: MIT
Keywords: claude,claude_chat
Author: Kammari Santhosh
Requires-Python: >=3.10,<4.0
Classifier: License :: OSI Approved :: MIT License
Classifier: Programming Language :: Python :: 3
Classifier: Programming Language :: Python :: 3.10
Classifier: Programming Language :: Python :: 3.11
Classifier: Programming Language :: Python :: 3.12
Classifier: Programming Language :: Python :: 3.13
Requires-Dist: ailitellm (>=0.1.3,<0.2.0)
Requires-Dist: streamlit (>=1.40.2,<2.0.0)
Project-URL: Repository, https://github.cov0m/username/sa
